{
  "id": "120572351",
  "premium": false,
  "billing_type": {
    "id": "standard",
    "name": "Стандарт"
  },
  "relations": [],
  "name": "Системный администратор",
  "insider_interview": null,
  "response_letter_required": false,
  "area": {
    "id": "1",
    "name": "Москва",
    "url": "https://api.hh.ru/areas/1"
  },
  "salary": null,
  "salary_range": null,
  "type": {
    "id": "open",
    "name": "Открытая"
  },
  "address": {
    "city": "Москва",
    "street": "Марксистская улица",
    "building": "34к8",
    "lat": 55.734851,
    "lng": 37.665138,
    "description": null,
    "raw": "Москва, Марксистская улица, 34к8",
    "metro": null,
    "metro_stations": []
  },
  "allow_messages": false,
  "experience": {
    "id": "between3And6",
    "name": "От 3 до 6 лет"
  },
  "schedule": {
    "id": "fullDay",
    "name": "Полный день"
  },
  "employment": {
    "id": "full",
    "name": "Полная занятость"
  },
  "department": null,
  "show_contacts": false,
  "contacts": null,
  "description": "<p><strong>IT2G - это системный интегратор комплексных проектов.</strong></p> <p>Мы выполняем полный цикл работ по реализации программных и инфраструктурных проектов для крупных государственных Заказчиков, рефакторинг, поддержку и развитие уже существующих проектов.</p> <p><strong>Мы являемся аккредитованной IT-компанией.</strong></p> <p>Штаб-квартира (с производством и проектным офисом) расположена в г. Москве. Обособленные подразделения &quot;Производственный RnD центр&quot; находятся в Саратове, Кемерово, Краснодаре, Самаре, Тюмени, Санкт-Петербурге.</p> <p>В связи с усилением существующих проектных и производственных команд мы ищем<strong> Эксперта поддержки инфраструктуры:</strong></p> <p><strong>Что мы ожидаем от тебя:</strong></p> <ul> <li> <p>опыт поддержки и настройки Windows Server;</p> </li> <li> <p>опыт поддержки и настройки Linux серверов;</p> </li> <li> <p>умение диагностировать проблемы с ОС и сетями;</p> </li> <li> <p>навыки работы с активным сетевым оборудованием. Понимание принципов работы стека протоколов TCP/IP;</p> </li> <li> <p>понимание принципов обеспечения информационной безопасности;</p> </li> <li> <p>опыт работы с системами виртуализации;</p> </li> <li> <p>опыт работы от 5 лет;</p> </li> <li> <p>владение ITSM-терминологией;</p> </li> <li> <p>грамотная устная и письменная речь;</p> </li> <li> <p>ответственность, желание развиваться в сфере IT, стремление к<strong> </strong>постоянному самообучению.</p> </li> </ul> <p><strong>Что предстоит делать:</strong></p> <ul> <li> <p>оказывать техническую поддержку сотрудников компании;</p> </li> <li> <p>администрировать системы виртуализации: VMware ESXi;</p> </li> <li> <p>администрировать локально-вычислительные сети;</p> </li> <li> <p>администрировать серверы Windows / Linux;</p> </li> <li> <p>настраивать и вести мониторинг системы резервного копирования (Veeam Backup);</p> </li> <li> <p>администрировать Sharepoint, Confluence, JIRA, GLPI, OpenVPN;</p> </li> <li> <p>внедрять и поддерживать корпоративные сервисов.</p> </li> </ul> <p><strong>Мы предлагаем:</strong></p> <ul> <li> <p>конкурентную заработную плату - обсудим на собеседовании;</p> </li> <li> <p>оформление по ТК РФ;</p> </li> <li> <p>ДМС после испытательного срока;</p> </li> <li> <p>100% оплата больничного;</p> </li> <li> <p>гибкое начало рабочего дня;</p> </li> <li> <p>возможность профессионального и карьерного роста - нам важно, чтобы наши сотрудники развивались.</p> </li> </ul>",
  "branded_description": null,
  "vacancy_constructor_template": null,
  "key_skills": [],
  "accept_handicapped": false,
  "accept_kids": false,
  "archived": false,
  "response_url": null,
  "specializations": [],
  "professional_roles": [
    {
      "id": "113",
      "name": "Системный администратор"
    }
  ],
  "code": null,
  "hidden": false,
  "quick_responses_allowed": false,
  "driver_license_types": [],
  "accept_incomplete_resumes": false,
  "employer": {
    "id": "2754726",
    "name": "IT2G",
    "url": "https://api.hh.ru/employers/2754726",
    "alternate_url": "https://hh.ru/employer/2754726",
    "logo_urls": {
      "original": "https://img.hhcdn.ru/employer-logo-original/498722.png",
      "90": "https://img.hhcdn.ru/employer-logo/2436641.png",
      "240": "https://img.hhcdn.ru/employer-logo/2436642.png"
    },
    "vacancies_url": "https://api.hh.ru/vacancies?employer_id=2754726",
    "accredited_it_employer": false,
    "trusted": true
  },
  "published_at": "2025-05-15T10:18:49+0300",
  "created_at": "2025-05-15T10:18:49+0300",
  "initial_created_at": "2025-05-15T10:18:49+0300",
  "negotiations_url": null,
  "suitable_resumes_url": null,
  "apply_alternate_url": "https://hh.ru/applicant/vacancy_response?vacancyId=120572351",
  "has_test": false,
  "test": null,
  "alternate_url": "https://hh.ru/vacancy/120572351",
  "working_days": [],
  "working_time_intervals": [],
  "working_time_modes": [],
  "accept_temporary": false,
  "languages": [],
  "approved": true,
  "employment_form": {
    "id": "FULL",
    "name": "Полная"
  },
  "fly_in_fly_out_duration": [],
  "internship": false,
  "night_shifts": false,
  "work_format": [
    {
      "id": "HYBRID",
      "name": "Гибрид"
    }
  ],
  "work_schedule_by_days": [
    {
      "id": "FIVE_ON_TWO_OFF",
      "name": "5/2"
    }
  ],
  "working_hours": [
    {
      "id": "HOURS_8",
      "name": "8 часов"
    }
  ],
  "show_logo_in_search": null
}